zynet/__init__.py
zynet/genWegitsAndBias.py
zynet/gen_nn.py
zynet/utils.py
zynet/xilinxUtils.py
zynet/zynet.py
zynet/db/Sig_ROM.v
zynet/db/Weight_Memory.v
zynet/db/axi_lite_wrapper.v
zynet/db/block.tcl
zynet/db/layerInterface
zynet/db/makeIP.tcl
zynet/db/maxFinder.v
zynet/db/moduleTemplate
zynet/db/neuron.v
zynet/db/relu.v
zynet/db/top_sim.v
zynet/db/vivadoScript.tcl
zynet-0.4.dist-info/LICENSE
zynet-0.4.dist-info/METADATA
zynet-0.4.dist-info/WHEEL
zynet-0.4.dist-info/top_level.txt
zynet-0.4.dist-info/RECORD
