Metadata-Version: 2.1
Name: zynet
Version: 0.4
Summary: Zynet FPGA DNN generator package
Home-page: https://github.com/dsdnu/zynet
Author: UNKNOWN
Author-email: UNKNOWN
License: MIT
Platform: UNKNOWN
